LICENCE
README.md
pyproject.toml
setup.py
spatools/__init__.py
spatools/constants.py
spatools.egg-info/PKG-INFO
spatools.egg-info/SOURCES.txt
spatools.egg-info/dependency_links.txt
spatools.egg-info/entry_points.txt
spatools.egg-info/requires.txt
spatools.egg-info/top_level.txt
spatools/plotting/__init__.py
spatools/plotting/pl.py
spatools/preprocessing/__init__.py
spatools/preprocessing/pp.py
spatools/reading/__init__.py
spatools/reading/read.py
spatools/tools/__init__.py
spatools/tools/tl.py