Metadata-Version: 2.1
Name: spatools
Version: 0.0.91
Author: Pedro Videira Pinho, Mariana Boroni
Author-email: Pedro Videira Pinho <pedrovp161@gmail.com>, Mariana Lima Boroni Martins <mariana.boroni@inca.gov.br>
License: MIT
Project-URL: Homepage, https://pypi.org/project/spatools/
Project-URL: Repository, https://github.com/pedrovp161/spatools
Classifier: Programming Language :: Python :: 3
Classifier: License :: OSI Approved :: MIT License
Requires-Python: >=3.9
License-File: LICENCE
Requires-Dist: scanpy>=1.10.1
Requires-Dist: pybiomart
Requires-Dist: scikit-image
Provides-Extra: dev
Requires-Dist: twine>=5.1.1; extra == "dev"
